robotpy_toolkit_7407/__init__.py
robotpy_toolkit_7407/command.py
robotpy_toolkit_7407/motor.py
robotpy_toolkit_7407/motors/__init__.py
robotpy_toolkit_7407/motors/ctre_motors.py
robotpy_toolkit_7407/motors/rev_motors.py
robotpy_toolkit_7407/oi/__init__.py
robotpy_toolkit_7407/oi/buttons.py
robotpy_toolkit_7407/oi/controllermap.py
robotpy_toolkit_7407/oi/joysticks.py
robotpy_toolkit_7407/pneumatics/__init__.py
robotpy_toolkit_7407/pneumatics/compressor.py
robotpy_toolkit_7407/pneumatics/pistons/__init__.py
robotpy_toolkit_7407/pneumatics/pistons/double_solenoid.py
robotpy_toolkit_7407/pneumatics/pistons/single_solenoid.py
robotpy_toolkit_7407/sensors/__init__.py
robotpy_toolkit_7407/sensors/color_sensors/REVColorSensor.py
robotpy_toolkit_7407/sensors/color_sensors/__init__.py
robotpy_toolkit_7407/sensors/gyro/ADIS16448.py
robotpy_toolkit_7407/sensors/gyro/PigeonIMU.py
robotpy_toolkit_7407/sensors/gyro/__init__.py
robotpy_toolkit_7407/sensors/gyro/base_gyro.py
robotpy_toolkit_7407/sensors/limelight/__init__.py
robotpy_toolkit_7407/sensors/limelight/limelight.py
robotpy_toolkit_7407/sensors/limit_switches/__init__.py
robotpy_toolkit_7407/sensors/limit_switches/limit_switch.py
robotpy_toolkit_7407/sensors/odometry/__init__.py
robotpy_toolkit_7407/sensors/odometry/vision_estimator.py
robotpy_toolkit_7407/sensors/photonvision/__init__.py
robotpy_toolkit_7407/sensors/photonvision/photon_camera.py
robotpy_toolkit_7407/sensors/photonvision/photon_odometry.py
robotpy_toolkit_7407/sensors/photonvision/photon_target.py
robotpy_toolkit_7407/subsystem.py
robotpy_toolkit_7407/subsystem_templates/__init__.py
robotpy_toolkit_7407/subsystem_templates/drivetrain/__init__.py
robotpy_toolkit_7407/subsystem_templates/drivetrain/differential_drivetrain.py
robotpy_toolkit_7407/subsystem_templates/drivetrain/differential_drivetrain_commands.py
robotpy_toolkit_7407/subsystem_templates/drivetrain/swerve_drivetrain.py
robotpy_toolkit_7407-2023.2.0.0.dist-info/METADATA
robotpy_toolkit_7407-2023.2.0.0.dist-info/WHEEL
robotpy_toolkit_7407-2023.2.0.0.dist-info/RECORD
