Metadata-Version: 2.1
Name: robotpy-toolkit-7407
Version: 2023.2.0.0
Summary: FRC Wired Boars Team 7407's Toolkit for usage with RobotPy
Author: Sidharth Rao
Author-email: sidharthmrao@gmail.com
Requires-Python: >3.9,<3.12
Classifier: Programming Language :: Python :: 3
Classifier: Programming Language :: Python :: 3.10
Classifier: Programming Language :: Python :: 3.11
Requires-Dist: m2r2 (>=0.3.3,<0.4.0)
Requires-Dist: pynetworktables (>=2021.0.0,<2022.0.0)
Requires-Dist: robotpy-apriltag (>=2023.1.1.0,<2024.0.0.0)
Requires-Dist: robotpy-ctre (>=2023.0.0,<2024.0.0)
Requires-Dist: robotpy-photonvision (>=2023.1.2,<2024.0.0)
Requires-Dist: robotpy-rev (>=2023.1.1,<2024.0.0)
Requires-Dist: robotpy[commands2] (>=2023.4.2.1,<2024.0.0.0)
